{
    "number": 1,
    "timestep_list": [
        {
            "number": 1,
            "state": {
                "two_finger_gripper": {
                    "pose": [
                        [
                            0.0,
                            0.0,
                            0.03
                        ],
                        [
                            0.0,
                            0.0,
                            0.0,
                            1.0
                        ]
                    ],
                    "joint_angles": {
                        "finger0_segment0_joint": -0.695,
                        "finger0_segment1_joint": 1.487,
                        "finger1_segment0_joint": 0.695,
                        "finger1_segment1_joint": -1.487
                    }
                },
                "obj_2": {
                    "pose": [
                        [
                            0.0,
                            0.1067,
                            0.05
                        ],
                        [
                            0.0,
                            0.0,
                            0.0,
                            1.0
                        ]
                    ]
                }
            },
            "reward": {
                "distance_to_goal": 0.0996937868061805,
                "goal_position": [
                    0.0,
                    0.2067,
                    0
                ]
            },
            "action": {
                "target_joint_angles": [
                    -0.07962536594435504,
                    0.07653605315253799,
                    0.07894584158129836,
                    -0.07560098738084996
                ]
            }
        },
        {
            "number": 2,
            "state": {
                "two_finger_gripper": {
                    "pose": [
                        [
                            0.0,
                            0.0,
                            0.03
                        ],
                        [
                            0.0,
                            0.0,
                            0.0,
                            1.0
                        ]
                    ],
                    "joint_angles": {
                        "finger0_segment0_joint": -0.6952415655233269,
                        "finger0_segment1_joint": 1.4809569865715546,
                        "finger1_segment0_joint": 0.695237686610873,
                        "finger1_segment1_joint": -1.4809519230835044
                    }
                },
                "obj_2": {
                    "pose": [
                        [
                            3.482774728640315e-05,
                            0.10700621927730804,
                            0.05002339065464914
                        ],
                        [
                            0.0012564306176148503,
                            2.91523096773202e-06,
                            -6.470404391383097e-07,
                            0.9999992106862814
                        ]
                    ]
                }
            },
            "reward": {
                "distance_to_goal": 0.09932580196647267,
                "goal_position": [
                    0.0,
                    0.2067,
                    0
                ]
            },
            "action": {
                "target_joint_angles": [
                    -0.07962536594435504,
                    0.07653605315253799,
                    0.07894584158129836,
                    -0.07560098738084996
                ]
            }
        },
        {
            "number": 3,
            "state": {
                "two_finger_gripper": {
                    "pose": [
                        [
                            0.0,
                            0.0,
                            0.03
                        ],
                        [
                            0.0,
                            0.0,
                            0.0,
                            1.0
                        ]
                    ],
                    "joint_angles": {
                        "finger0_segment0_joint": -0.6948495115312749,
                        "finger0_segment1_joint": 1.473879691582397,
                        "finger1_segment0_joint": 0.6948410631521131,
                        "finger1_segment1_joint": -1.473884952606253
                    }
                },
                "obj_2": {
                    "pose": [
                        [
                            6.078679641712315e-05,
                            0.10737421663410689,
                            0.05004010051013592
                        ],
                        [
                            0.0021527075115025545,
                            1.1467439335866393e-06,
                            4.3336334135444756e-05,
                            0.9999976819828219
                        ]
                    ]
                }
            },
            "reward": {
                "distance_to_goal": 0.09888616426400851,
                "goal_position": [
                    0.0,
                    0.2067,
                    0
                ]
            },
            "action": {
                "target_joint_angles": [
                    -0.07962536594435504,
                    0.07653605315253799,
                    0.07894584158129836,
                    -0.07560098738084996
                ]
            }
        },
        {
            "number": 4,
            "state": {
                "two_finger_gripper": {
                    "pose": [
                        [
                            0.0,
                            0.0,
                            0.03
                        ],
                        [
                            0.0,
                            0.0,
                            0.0,
                            1.0
                        ]
                    ],
                    "joint_angles": {
                        "finger0_segment0_joint": -0.6936564260478191,
                        "finger0_segment1_joint": 1.4654948013255962,
                        "finger1_segment0_joint": 0.6936328642120388,
                        "finger1_segment1_joint": -1.4655244758393078
                    }
                },
                "obj_2": {
                    "pose": [
                        [
                            8.516810480010999e-05,
                            0.10781387241254514,
                            0.050051253396038546
                        ],
                        [
                            0.0027562462350214697,
                            -5.269801707779064e-07,
                            9.759719298281684e-05,
                            0.9999961967833688
                        ]
                    ]
                }
            },
            "reward": {
                "distance_to_goal": 0.09838067747175953,
                "goal_position": [
                    0.0,
                    0.2067,
                    0
                ]
            },
            "action": {
                "target_joint_angles": [
                    -0.07962536594435504,
                    0.07653605315253799,
                    0.07894584158129836,
                    -0.07560098738084996
                ]
            }
        },
        {
            "number": 5,
            "state": {
                "two_finger_gripper": {
                    "pose": [
                        [
                            0.0,
                            0.0,
                            0.03
                        ],
                        [
                            0.0,
                            0.0,
                            0.0,
                            1.0
                        ]
                    ],
                    "joint_angles": {
                        "finger0_segment0_joint": -0.6917309379901613,
                        "finger0_segment1_joint": 1.455937069018735,
                        "finger1_segment0_joint": 0.6916880061358271,
                        "finger1_segment1_joint": -1.4559885028285544
                    }
                },
                "obj_2": {
                    "pose": [
                        [
                            0.00010776156021213145,
                            0.10831938154672682,
                            0.05005633253649037
                        ],
                        [
                            0.0030290319168413916,
                            -1.2251528726321452e-06,
                            0.0001467093773521736,
                            0.99999540170968
                        ]
                    ]
                }
            },
            "reward": {
                "distance_to_goal": 0.09781935638733483,
                "goal_position": [
                    0.0,
                    0.2067,
                    0
                ]
            },
            "action": {
                "target_joint_angles": [
                    -0.07962536594435504,
                    0.07653605315253799,
                    0.07894584158129836,
                    -0.07560098738084996
                ]
            }
        },
        {
            "number": 6,
            "state": {
                "two_finger_gripper": {
                    "pose": [
                        [
                            0.0,
                            0.0,
                            0.03
                        ],
                        [
                            0.0,
                            0.0,
                            0.0,
                            1.0
                        ]
                    ],
                    "joint_angles": {
                        "finger0_segment0_joint": -0.6891523110300619,
                        "finger0_segment1_joint": 1.445330778090659,
                        "finger1_segment0_joint": 0.689082254539239,
                        "finger1_segment1_joint": -1.445410098816327
                    }
                },
                "obj_2": {
                    "pose": [
                        [
                            0.00013060244709806428,
                            0.10888073079892062,
                            0.050055993830092786
                        ],
                        [
                            0.003011026125673976,
                            -1.3893686428022727e-06,
                            0.0001646656774263327,
                            0.9999954532921411
                        ]
                    ]
                }
            },
            "reward": {
                "distance_to_goal": 0.0972079507822577,
                "goal_position": [
                    0.0,
                    0.2067,
                    0
                ]
            },
            "action": {
                "target_joint_angles": [
                    -0.07962536594435504,
                    0.07653605315253799,
                    0.07894584158129836,
                    -0.07560098738084996
                ]
            }
        },
        {
            "number": 7,
            "state": {
                "two_finger_gripper": {
                    "pose": [
                        [
                            0.0,
                            0.0,
                            0.03
                        ],
                        [
                            0.0,
                            0.0,
                            0.0,
                            1.0
                        ]
                    ],
                    "joint_angles": {
                        "finger0_segment0_joint": -0.6859638452048429,
                        "finger0_segment1_joint": 1.433791240065736,
                        "finger1_segment0_joint": 0.6858865721337112,
                        "finger1_segment1_joint": -1.4338955211972964
                    }
                },
                "obj_2": {
                    "pose": [
                        [
                            0.00015086931574698708,
                            0.10949216629440094,
                            0.05005005224397046
                        ],
                        [
                            0.002697428209977141,
                            -1.6104968658225353e-06,
                            0.00017212731631774798,
                            0.9999963471186509
                        ]
                    ]
                }
            },
            "reward": {
                "distance_to_goal": 0.09654862142158326,
                "goal_position": [
                    0.0,
                    0.2067,
                    0
                ]
            },
            "action": {
                "target_joint_angles": [
                    -0.07962536594435504,
                    0.07653605315253799,
                    0.07894584158129836,
                    -0.07560098738084996
                ]
            }
        },
        {
            "number": 8,
            "state": {
                "two_finger_gripper": {
                    "pose": [
                        [
                            0.0,
                            0.0,
                            0.03
                        ],
                        [
                            0.0,
                            0.0,
                            0.0,
                            1.0
                        ]
                    ],
                    "joint_angles": {
                        "finger0_segment0_joint": -0.6821993805969921,
                        "finger0_segment1_joint": 1.421366189803497,
                        "finger1_segment0_joint": 0.6821402678057095,
                        "finger1_segment1_joint": -1.4215328139868828
                    }
                },
                "obj_2": {
                    "pose": [
                        [
                            0.00016842648000496262,
                            0.11015152548626654,
                            0.050038274278985016
                        ],
                        [
                            0.0020745198672344482,
                            -1.7720641585604973e-06,
                            0.0002030627162858449,
                            0.999997827562497
                        ]
                    ]
                }
            },
            "reward": {
                "distance_to_goal": 0.09584463706920292,
                "goal_position": [
                    0.0,
                    0.2067,
                    0
                ]
            },
            "action": {
                "target_joint_angles": [
                    -0.07962536594435504,
                    0.07653605315253799,
                    0.07894584158129836,
                    -0.07560098738084996
                ]
            }
        },
        {
            "number": 9,
            "state": {
                "two_finger_gripper": {
                    "pose": [
                        [
                            0.0,
                            0.0,
                            0.03
                        ],
                        [
                            0.0,
                            0.0,
                            0.0,
                            1.0
                        ]
                    ],
                    "joint_angles": {
                        "finger0_segment0_joint": -0.6779129727958306,
                        "finger0_segment1_joint": 1.4081438936934196,
                        "finger1_segment0_joint": 0.6778699605895006,
                        "finger1_segment1_joint": -1.4083648053500863
                    }
                },
                "obj_2": {
                    "pose": [
                        [
                            0.00018425147819477766,
                            0.11085554003323922,
                            0.05002022822895147
                        ],
                        [
                            0.0011208605594371542,
                            -1.9831430823032576e-06,
                            0.00023069673788957243,
                            0.9999993452231299
                        ]
                    ]
                }
            },
            "reward": {
                "distance_to_goal": 0.09509949312887304,
                "goal_position": [
                    0.0,
                    0.2067,
                    0
                ]
            },
            "action": {
                "target_joint_angles": [
                    -0.07962536594435504,
                    0.07653605315253799,
                    0.07894584158129836,
                    -0.07560098738084996
                ]
            }
        },
        {
            "number": 10,
            "state": {
                "two_finger_gripper": {
                    "pose": [
                        [
                            0.0,
                            0.0,
                            0.03
                        ],
                        [
                            0.0,
                            0.0,
                            0.0,
                            1.0
                        ]
                    ],
                    "joint_angles": {
                        "finger0_segment0_joint": -0.6731517911909141,
                        "finger0_segment1_joint": 1.3941700388361087,
                        "finger1_segment0_joint": 0.6731216699566658,
                        "finger1_segment1_joint": -1.394452370761697
                    }
                },
                "obj_2": {
                    "pose": [
                        [
                            0.00019979632824915504,
                            0.11160071674930568,
                            0.04999567499605513
                        ],
                        [
                            -0.00016967767677065945,
                            -2.5475520225186008e-06,
                            0.00027682046180527116,
                            0.9999999472867125
                        ]
                    ]
                }
            },
            "reward": {
                "distance_to_goal": 0.09431714364358315,
                "goal_position": [
                    0.0,
                    0.2067,
                    0
                ]
            },
            "action": {
                "target_joint_angles": [
                    -0.07962536594435504,
                    0.07653605315253799,
                    0.07894584158129836,
                    -0.07560098738084996
                ]
            }
        },
        {
            "number": 11,
            "state": {
                "two_finger_gripper": {
                    "pose": [
                        [
                            0.0,
                            0.0,
                            0.03
                        ],
                        [
                            0.0,
                            0.0,
                            0.0,
                            1.0
                        ]
                    ],
                    "joint_angles": {
                        "finger0_segment0_joint": -0.6679384739884479,
                        "finger0_segment1_joint": 1.3795135447871765,
                        "finger1_segment0_joint": 0.6679482228550481,
                        "finger1_segment1_joint": -1.3799038996007498
                    }
                },
                "obj_2": {
                    "pose": [
                        [
                            0.00021286580982155851,
                            0.11238309656678021,
                            0.049964118856065005
                        ],
                        [
                            -0.0018233781680497682,
                            -3.301079175162435e-06,
                            0.00035281052346892067,
                            0.9999982754014597
                        ]
                    ]
                }
            },
            "reward": {
                "distance_to_goal": 0.09350086905053556,
                "goal_position": [
                    0.0,
                    0.2067,
                    0
                ]
            },
            "action": {
                "target_joint_angles": [
                    -0.07962536594435504,
                    0.07653605315253799,
                    0.07894584158129836,
                    -0.07560098738084996
                ]
            }
        },
        {
            "number": 12,
            "state": {
                "two_finger_gripper": {
                    "pose": [
                        [
                            0.0,
                            0.0,
                            0.03
                        ],
                        [
                            0.0,
                            0.0,
                            0.0,
                            1.0
                        ]
                    ],
                    "joint_angles": {
                        "finger0_segment0_joint": -0.6623340565879589,
                        "finger0_segment1_joint": 1.3642712924611826,
                        "finger1_segment0_joint": 0.6623672450559822,
                        "finger1_segment1_joint": -1.3647556610256815
                    }
                },
                "obj_2": {
                    "pose": [
                        [
                            0.0002250368484282678,
                            0.11319940175794463,
                            0.04992503712039829
                        ],
                        [
                            -0.0038628953738106407,
                            -4.312386335737753e-06,
                            0.00042322195106787907,
                            0.9999924494234516
                        ]
                    ]
                }
            },
            "reward": {
                "distance_to_goal": 0.0926516973187435,
                "goal_position": [
                    0.0,
                    0.2067,
                    0
                ]
            },
            "action": {
                "target_joint_angles": [
                    -0.07962536594435504,
                    0.07653605315253799,
                    0.07894584158129836,
                    -0.07560098738084996
                ]
            }
        },
        {
            "number": 13,
            "state": {
                "two_finger_gripper": {
                    "pose": [
                        [
                            0.0,
                            0.0,
                            0.03
                        ],
                        [
                            0.0,
                            0.0,
                            0.0,
                            1.0
                        ]
                    ],
                    "joint_angles": {
                        "finger0_segment0_joint": -0.6563521366949006,
                        "finger0_segment1_joint": 1.3484618153034575,
                        "finger1_segment0_joint": 0.6563935519051892,
                        "finger1_segment1_joint": -1.349013492824914
                    }
                },
                "obj_2": {
                    "pose": [
                        [
                            0.00023635560140289756,
                            0.11404860415474709,
                            0.0498781605248003
                        ],
                        [
                            -0.006295724739149912,
                            -5.64421479661908e-06,
                            0.0004790651284968928,
                            0.9999800669587141
                        ]
                    ]
                }
            },
            "reward": {
                "distance_to_goal": 0.09177074623567325,
                "goal_position": [
                    0.0,
                    0.2067,
                    0
                ]
            },
            "action": {
                "target_joint_angles": [
                    -0.07962536594435504,
                    0.07653605315253799,
                    0.07894584158129836,
                    -0.07560098738084996
                ]
            }
        },
        {
            "number": 14,
            "state": {
                "two_finger_gripper": {
                    "pose": [
                        [
                            0.0,
                            0.0,
                            0.03
                        ],
                        [
                            0.0,
                            0.0,
                            0.0,
                            1.0
                        ]
                    ],
                    "joint_angles": {
                        "finger0_segment0_joint": -0.6500015047829725,
                        "finger0_segment1_joint": 1.3320882838093044,
                        "finger1_segment0_joint": 0.6500494457884923,
                        "finger1_segment1_joint": -1.3327002228924976
                    }
                },
                "obj_2": {
                    "pose": [
                        [
                            0.0002467268200662229,
                            0.11492958542902514,
                            0.04982323358303544
                        ],
                        [
                            -0.009127193822669534,
                            -7.529553356471455e-06,
                            0.0005297989942000714,
                            0.999958205921255
                        ]
                    ]
                }
            },
            "reward": {
                "distance_to_goal": 0.0908543195299635,
                "goal_position": [
                    0.0,
                    0.2067,
                    0
                ]
            },
            "action": {
                "target_joint_angles": [
                    -0.07962536594435504,
                    0.07653605315253799,
                    0.07894584158129836,
                    -0.07560098738084996
                ]
            }
        },
        {
            "number": 15,
            "state": {
                "two_finger_gripper": {
                    "pose": [
                        [
                            0.0,
                            0.0,
                            0.03
                        ],
                        [
                            0.0,
                            0.0,
                            0.0,
                            1.0
                        ]
                    ],
                    "joint_angles": {
                        "finger0_segment0_joint": -0.6433429016935871,
                        "finger0_segment1_joint": 1.3152013267414964,
                        "finger1_segment0_joint": 0.6433786629815718,
                        "finger1_segment1_joint": -1.315845223268523
                    }
                },
                "obj_2": {
                    "pose": [
                        [
                            0.0002561578405011497,
                            0.11584604158093352,
                            0.049751120954049634
                        ],
                        [
                            -0.012483547120209125,
                            -5.85043520569077e-06,
                            0.0005472961191270345,
                            0.9999219276943715
                        ]
                    ]
                }
            },
            "reward": {
                "distance_to_goal": 0.08990683990019108,
                "goal_position": [
                    0.0,
                    0.2067,
                    0
                ]
            },
            "action": {
                "target_joint_angles": [
                    -0.07962536594435504,
                    0.07653605315253799,
                    0.07894584158129836,
                    -0.07560098738084996
                ]
            }
        },
        {
            "number": 16,
            "state": {
                "two_finger_gripper": {
                    "pose": [
                        [
                            0.0,
                            0.0,
                            0.03
                        ],
                        [
                            0.0,
                            0.0,
                            0.0,
                            1.0
                        ]
                    ],
                    "joint_angles": {
                        "finger0_segment0_joint": -0.6363746174387037,
                        "finger0_segment1_joint": 1.2978315395671176,
                        "finger1_segment0_joint": 0.636397125788168,
                        "finger1_segment1_joint": -1.2985234991964532
                    }
                },
                "obj_2": {
                    "pose": [
                        [
                            0.0002642441250529575,
                            0.11679354841903188,
                            0.04966565991611415
                        ],
                        [
                            -0.01642276285910104,
                            -4.6357189668876735e-06,
                            0.0005744851234268875,
                            0.9998649722864716
                        ]
                    ]
                }
            },
            "reward": {
                "distance_to_goal": 0.08904221442167343,
                "goal_position": [
                    0.0,
                    0.2067,
                    0
                ]
            },
            "action": {
                "target_joint_angles": [
                    -0.07962536594435504,
                    0.07653605315253799,
                    0.07894584158129836,
                    -0.07560098738084996
                ]
            }
        },
        {
            "number": 17,
            "state": {
                "two_finger_gripper": {
                    "pose": [
                        [
                            0.0,
                            0.0,
                            0.03
                        ],
                        [
                            0.0,
                            0.0,
                            0.0,
                            1.0
                        ]
                    ],
                    "joint_angles": {
                        "finger0_segment0_joint": -0.6291073171863166,
                        "finger0_segment1_joint": 1.2802075189649875,
                        "finger1_segment0_joint": 0.6291307127720891,
                        "finger1_segment1_joint": -1.2807339784034955
                    }
                },
                "obj_2": {
                    "pose": [
                        [
                            0.000268570663748966,
                            0.11765819061298315,
                            0.04964700421515352
                        ],
                        [
                            -0.01732329560507584,
                            -3.740629034698969e-05,
                            0.00046100866614039784,
                            0.9998498334755866
                        ]
                    ]
                }
            },
            "reward": {
                "distance_to_goal": 0.088178822167808,
                "goal_position": [
                    0.0,
                    0.2067,
                    0
                ]
            },
            "action": {
                "target_joint_angles": [
                    -0.07962536594435504,
                    0.07653605315253799,
                    0.07894584158129836,
                    -0.07560098738084996
                ]
            }
        },
        {
            "number": 18,
            "state": {
                "two_finger_gripper": {
                    "pose": [
                        [
                            0.0,
                            0.0,
                            0.03
                        ],
                        [
                            0.0,
                            0.0,
                            0.0,
                            1.0
                        ]
                    ],
                    "joint_angles": {
                        "finger0_segment0_joint": -0.621552211219659,
                        "finger0_segment1_joint": 1.2618149746699796,
                        "finger1_segment0_joint": 0.62157586801299,
                        "finger1_segment1_joint": -1.2625277196454228
                    }
                },
                "obj_2": {
                    "pose": [
                        [
                            0.0002732742188157654,
                            0.11852160128408297,
                            0.04964251554594258
                        ],
                        [
                            -0.01748643172786669,
                            -2.9266818867013877e-05,
                            0.0005708519611714896,
                            0.9998469372743602
                        ]
                    ]
                }
            },
            "reward": {
                "distance_to_goal": 0.0873101309690732,
                "goal_position": [
                    0.0,
                    0.2067,
                    0
                ]
            },
            "action": {
                "target_joint_angles": [
                    -0.07962536594435504,
                    0.07653605315253799,
                    0.07894584158129836,
                    -0.07560098738084996
                ]
            }
        },
        {
            "number": 19,
            "state": {
                "two_finger_gripper": {
                    "pose": [
                        [
                            0.0,
                            0.0,
                            0.03
                        ],
                        [
                            0.0,
                            0.0,
                            0.0,
                            1.0
                        ]
                    ],
                    "joint_angles": {
                        "finger0_segment0_joint": -0.6137326145796157,
                        "finger0_segment1_joint": 1.2430725668818474,
                        "finger1_segment0_joint": 0.6137391469209021,
                        "finger1_segment1_joint": -1.2437982296900776
                    }
                },
                "obj_2": {
                    "pose": [
                        [
                            0.000278127482044078,
                            0.11939031202128571,
                            0.04964241312119815
                        ],
                        [
                            -0.017470209046467153,
                            -2.582178011831552e-05,
                            0.0005762279303797019,
                            0.9998472178740513
                        ]
                    ]
                }
            },
            "reward": {
                "distance_to_goal": 0.08643276896245125,
                "goal_position": [
                    0.0,
                    0.2067,
                    0
                ]
            },
            "action": {
                "target_joint_angles": [
                    -0.07962536594435504,
                    0.07653605315253799,
                    0.07894584158129836,
                    -0.07560098738084996
                ]
            }
        },
        {
            "number": 20,
            "state": {
                "two_finger_gripper": {
                    "pose": [
                        [
                            0.0,
                            0.0,
                            0.03
                        ],
                        [
                            0.0,
                            0.0,
                            0.0,
                            1.0
                        ]
                    ],
                    "joint_angles": {
                        "finger0_segment0_joint": -0.6056603816484312,
                        "finger0_segment1_joint": 1.2239368591685793,
                        "finger1_segment0_joint": 0.605644276048769,
                        "finger1_segment1_joint": -1.2246627616576866
                    }
                },
                "obj_2": {
                    "pose": [
                        [
                            0.00023418820841030372,
                            0.12026754830273806,
                            0.049642056138974294
                        ],
                        [
                            -0.01746633778608563,
                            -2.8405767209995424e-05,
                            0.0005693717112877281,
                            0.9998472893663858
                        ]
                    ]
                }
            },
            "reward": {
                "distance_to_goal": 0.0855455445097553,
                "goal_position": [
                    0.0,
                    0.2067,
                    0
                ]
            },
            "action": {
                "target_joint_angles": [
                    -0.07962536594435504,
                    0.07653605315253799,
                    0.07894584158129836,
                    -0.07560098738084996
                ]
            }
        },
        {
            "number": 21,
            "state": {
                "two_finger_gripper": {
                    "pose": [
                        [
                            0.0,
                            0.0,
                            0.03
                        ],
                        [
                            0.0,
                            0.0,
                            0.0,
                            1.0
                        ]
                    ],
                    "joint_angles": {
                        "finger0_segment0_joint": -0.5973248212095008,
                        "finger0_segment1_joint": 1.2043829638127859,
                        "finger1_segment0_joint": 0.5972859900797982,
                        "finger1_segment1_joint": -1.2050783943600352
                    }
                },
                "obj_2": {
                    "pose": [
                        [
                            0.0001976853822119674,
                            0.12115468390402556,
                            0.049642150463753754
                        ],
                        [
                            -0.0175057581738033,
                            3.964579191945448e-06,
                            0.0005413132162217537,
                            0.9998466159341863
                        ]
                    ]
                }
            },
            "reward": {
                "distance_to_goal": 0.08465218374375323,
                "goal_position": [
                    0.0,
                    0.2067,
                    0
                ]
            },
            "action": {
                "target_joint_angles": [
                    -0.07962536594435504,
                    0.07653605315253799,
                    0.07894584158129836,
                    -0.07560098738084996
                ]
            }
        },
        {
            "number": 22,
            "state": {
                "two_finger_gripper": {
                    "pose": [
                        [
                            0.0,
                            0.0,
                            0.03
                        ],
                        [
                            0.0,
                            0.0,
                            0.0,
                            1.0
                        ]
                    ],
                    "joint_angles": {
                        "finger0_segment0_joint": -0.5887345209994014,
                        "finger0_segment1_joint": 1.1844332803139281,
                        "finger1_segment0_joint": 0.5886747574206102,
                        "finger1_segment1_joint": -1.1850771417685355
                    }
                },
                "obj_2": {
                    "pose": [
                        [
                            0.00016185911596641175,
                            0.12204797099766161,
                            0.04964196121083683
                        ],
                        [
                            -0.01749195858037073,
                            1.857240854918257e-07,
                            0.0005043151661806019,
                            0.9998468768022437
                        ]
                    ]
                }
            },
            "reward": {
                "distance_to_goal": 0.0837481647167353,
                "goal_position": [
                    0.0,
                    0.2067,
                    0
                ]
            },
            "action": {
                "target_joint_angles": [
                    -0.07962536594435504,
                    0.07653605315253799,
                    0.07894584158129836,
                    -0.07560098738084996
                ]
            }
        },
        {
            "number": 23,
            "state": {
                "two_finger_gripper": {
                    "pose": [
                        [
                            0.0,
                            0.0,
                            0.03
                        ],
                        [
                            0.0,
                            0.0,
                            0.0,
                            1.0
                        ]
                    ],
                    "joint_angles": {
                        "finger0_segment0_joint": -0.579912269224328,
                        "finger0_segment1_joint": 1.1639887810924965,
                        "finger1_segment0_joint": 0.5798162767073829,
                        "finger1_segment1_joint": -1.1645833598399769
                    }
                },
                "obj_2": {
                    "pose": [
                        [
                            0.0001291919243023756,
                            0.122951934930602,
                            0.04964182211019718
                        ],
                        [
                            -0.017477625056432442,
                            -3.1015389441330885e-06,
                            0.00047066073462898,
                            0.9998471438631208
                        ]
                    ]
                }
            },
            "reward": {
                "distance_to_goal": 0.08283771221955179,
                "goal_position": [
                    0.0,
                    0.2067,
                    0
                ]
            },
            "action": {
                "target_joint_angles": [
                    -0.07962536594435504,
                    0.07653605315253799,
                    0.07894584158129836,
                    -0.07560098738084996
                ]
            }
        },
        {
            "number": 24,
            "state": {
                "two_finger_gripper": {
                    "pose": [
                        [
                            0.0,
                            0.0,
                            0.03
                        ],
                        [
                            0.0,
                            0.0,
                            0.0,
                            1.0
                        ]
                    ],
                    "joint_angles": {
                        "finger0_segment0_joint": -0.5708254346913086,
                        "finger0_segment1_joint": 1.1430925292398137,
                        "finger1_segment0_joint": 0.5707229708584289,
                        "finger1_segment1_joint": -1.1436981251258158
                    }
                },
                "obj_2": {
                    "pose": [
                        [
                            9.94221752677005e-05,
                            0.12386234744392895,
                            0.04964162752470073
                        ],
                        [
                            -0.0174663168157452,
                            -6.802941589852468e-06,
                            0.0004695617408160523,
                            0.9998473419689545
                        ]
                    ]
                }
            },
            "reward": {
                "distance_to_goal": 0.08192156480974598,
                "goal_position": [
                    0.0,
                    0.2067,
                    0
                ]
            },
            "action": {
                "target_joint_angles": [
                    -0.07962536594435504,
                    0.07653605315253799,
                    0.07894584158129836,
                    -0.07560098738084996
                ]
            }
        },
        {
            "number": 25,
            "state": {
                "two_finger_gripper": {
                    "pose": [
                        [
                            0.0,
                            0.0,
                            0.03
                        ],
                        [
                            0.0,
                            0.0,
                            0.0,
                            1.0
                        ]
                    ],
                    "joint_angles": {
                        "finger0_segment0_joint": -0.5615040327584425,
                        "finger0_segment1_joint": 1.121800351216056,
                        "finger1_segment0_joint": 0.5613693683414709,
                        "finger1_segment1_joint": -1.1223672187467437
                    }
                },
                "obj_2": {
                    "pose": [
                        [
                            7.387464930627389e-05,
                            0.12477846849934017,
                            0.04964129600653305
                        ],
                        [
                            -0.017461394543561794,
                            -9.910866099977381e-06,
                            0.0004425727393042638,
                            0.9998474402286277
                        ]
                    ]
                }
            },
            "reward": {
                "distance_to_goal": 0.08100025826064183,
                "goal_position": [
                    0.0,
                    0.2067,
                    0
                ]
            },
            "action": {
                "target_joint_angles": [
                    -0.07962536594435504,
                    0.07653605315253799,
                    0.07894584158129836,
                    -0.07560098738084996
                ]
            }
        },
        {
            "number": 26,
            "state": {
                "two_finger_gripper": {
                    "pose": [
                        [
                            0.0,
                            0.0,
                            0.03
                        ],
                        [
                            0.0,
                            0.0,
                            0.0,
                            1.0
                        ]
                    ],
                    "joint_angles": {
                        "finger0_segment0_joint": -0.5519321875900342,
                        "finger0_segment1_joint": 1.1001178553784494,
                        "finger1_segment0_joint": 0.5517816976916085,
                        "finger1_segment1_joint": -1.1005754596103592
                    }
                },
                "obj_2": {
                    "pose": [
                        [
                            5.40419476902497e-05,
                            0.12569975976727868,
                            0.04964142368542386
                        ],
                        [
                            -0.017474615350492505,
                            1.0617529880561739e-05,
                            0.00037277558795691525,
                            0.9998472377038311
                        ]
                    ]
                }
            },
            "reward": {
                "distance_to_goal": 0.08007413051093935,
                "goal_position": [
                    0.0,
                    0.2067,
                    0
                ]
            },
            "action": {
                "target_joint_angles": [
                    -0.07962536594435504,
                    0.07653605315253799,
                    0.07894584158129836,
                    -0.07560098738084996
                ]
            }
        },
        {
            "number": 27,
            "state": {
                "two_finger_gripper": {
                    "pose": [
                        [
                            0.0,
                            0.0,
                            0.03
                        ],
                        [
                            0.0,
                            0.0,
                            0.0,
                            1.0
                        ]
                    ],
                    "joint_angles": {
                        "finger0_segment0_joint": -0.5421069171351908,
                        "finger0_segment1_joint": 1.0779951760808977,
                        "finger1_segment0_joint": 0.5419250157159858,
                        "finger1_segment1_joint": -1.0782999647019582
                    }
                },
                "obj_2": {
                    "pose": [
                        [
                            7.203237465916538e-05,
                            0.1266259018881889,
                            0.04964108211787543
                        ],
                        [
                            -0.017448790490032413,
                            3.210037569354716e-05,
                            0.0002807311398067958,
                            0.9998477183401621
                        ]
                    ]
                }
            },
            "reward": {
                "distance_to_goal": 0.079144770481773,
                "goal_position": [
                    0.0,
                    0.2067,
                    0
                ]
            },
            "action": {
                "target_joint_angles": [
                    -0.07962536594435504,
                    0.07653605315253799,
                    0.07894584158129836,
                    -0.07560098738084996
                ]
            }
        },
        {
            "number": 28,
            "state": {
                "two_finger_gripper": {
                    "pose": [
                        [
                            0.0,
                            0.0,
                            0.03
                        ],
                        [
                            0.0,
                            0.0,
                            0.0,
                            1.0
                        ]
                    ],
                    "joint_angles": {
                        "finger0_segment0_joint": -0.53202219001919,
                        "finger0_segment1_joint": 1.055391393079381,
                        "finger1_segment0_joint": 0.5318334918774286,
                        "finger1_segment1_joint": -1.0556948899478782
                    }
                },
                "obj_2": {
                    "pose": [
                        [
                            8.297234385603371e-05,
                            0.12755527301075148,
                            0.04964117774491694
                        ],
                        [
                            -0.01746752319579492,
                            1.0334982681660504e-05,
                            0.00028750288288281327,
                            0.9998473897894042
                        ]
                    ]
                }
            },
            "reward": {
                "distance_to_goal": 0.07821001140597496,
                "goal_position": [
                    0.0,
                    0.2067,
                    0
                ]
            },
            "action": {
                "target_joint_angles": [
                    -0.07962536594435504,
                    0.07653605315253799,
                    0.07894584158129836,
                    -0.07560098738084996
                ]
            }
        },
        {
            "number": 29,
            "state": {
                "two_finger_gripper": {
                    "pose": [
                        [
                            0.0,
                            0.0,
                            0.03
                        ],
                        [
                            0.0,
                            0.0,
                            0.0,
                            1.0
                        ]
                    ],
                    "joint_angles": {
                        "finger0_segment0_joint": -0.5216665031973832,
                        "finger0_segment1_joint": 1.0322846944653392,
                        "finger1_segment0_joint": 0.5214714390951023,
                        "finger1_segment1_joint": -1.0325888899310907
                    }
                },
                "obj_2": {
                    "pose": [
                        [
                            9.29188390947821e-05,
                            0.12849004379101037,
                            0.049641514331853036
                        ],
                        [
                            -0.017485837187466956,
                            -8.803741030322633e-06,
                            0.0002912549963435972,
                            0.999847068601431
                        ]
                    ]
                }
            },
            "reward": {
                "distance_to_goal": 0.07726810401567895,
                "goal_position": [
                    0.0,
                    0.2067,
                    0
                ]
            },
            "action": {
                "target_joint_angles": [
                    -0.07962536594435504,
                    0.07653605315253799,
                    0.07894584158129836,
                    -0.07560098738084996
                ]
            }
        },
        {
            "number": 30,
            "state": {
                "two_finger_gripper": {
                    "pose": [
                        [
                            0.0,
                            0.0,
                            0.03
                        ],
                        [
                            0.0,
                            0.0,
                            0.0,
                            1.0
                        ]
                    ],
                    "joint_angles": {
                        "finger0_segment0_joint": -0.5110257499562089,
                        "finger0_segment1_joint": 1.0085899473858195,
                        "finger1_segment0_joint": 0.5108167760623452,
                        "finger1_segment1_joint": -1.0088977820686722
                    }
                },
                "obj_2": {
                    "pose": [
                        [
                            0.00010166140718138015,
                            0.1294319628621506,
                            0.04964212012740512
                        ],
                        [
                            -0.017479854450466424,
                            -2.0320482160082194e-05,
                            0.00029484677817895446,
                            0.999847171992223
                        ]
                    ]
                }
            },
            "reward": {
                "distance_to_goal": 0.07632152295039935,
                "goal_position": [
                    0.0,
                    0.2067,
                    0
                ]
            },
            "action": {
                "target_joint_angles": [
                    -0.07962536594435504,
                    0.07653605315253799,
                    0.07894584158129836,
                    -0.07560098738084996
                ]
            }
        },
        {
            "number": 31,
            "state": {
                "two_finger_gripper": {
                    "pose": [
                        [
                            0.0,
                            0.0,
                            0.03
                        ],
                        [
                            0.0,
                            0.0,
                            0.0,
                            1.0
                        ]
                    ],
                    "joint_angles": {
                        "finger0_segment0_joint": -0.5000920632520879,
                        "finger0_segment1_joint": 0.984378786599862,
                        "finger1_segment0_joint": 0.49986726378275526,
                        "finger1_segment1_joint": -0.9846283005057549
                    }
                },
                "obj_2": {
                    "pose": [
                        [
                            0.00010930667673899251,
                            0.13037855532342987,
                            0.049642896415760016
                        ],
                        [
                            -0.01747104410793273,
                            -3.379551762918858e-05,
                            0.00026591098716630845,
                            0.9998473337299993
                        ]
                    ]
                }
            },
            "reward": {
                "distance_to_goal": 0.07537055756912303,
                "goal_position": [
                    0.0,
                    0.2067,
                    0
                ]
            },
            "action": {
                "target_joint_angles": [
                    -0.07962536594435504,
                    0.07653605315253799,
                    0.07894584158129836,
                    -0.07560098738084996
                ]
            }
        },
        {
            "number": 32,
            "state": {
                "two_finger_gripper": {
                    "pose": [
                        [
                            0.0,
                            0.0,
                            0.03
                        ],
                        [
                            0.0,
                            0.0,
                            0.0,
                            1.0
                        ]
                    ],
                    "joint_angles": {
                        "finger0_segment0_joint": -0.48885135004244196,
                        "finger0_segment1_joint": 0.9595928737745171,
                        "finger1_segment0_joint": 0.48862106244001213,
                        "finger1_segment1_joint": -0.9598012209745354
                    }
                },
                "obj_2": {
                    "pose": [
                        [
                            0.00011504496899977074,
                            0.13132953023275232,
                            0.049643420090288624
                        ],
                        [
                            -0.01747075948323072,
                            -4.630338861502512e-05,
                            0.0002465294286142622,
                            0.9998473431691041
                        ]
                    ]
                }
            },
            "reward": {
                "distance_to_goal": 0.07441590033184176,
                "goal_position": [
                    0.0,
                    0.2067,
                    0
                ]
            },
            "action": {
                "target_joint_angles": [
                    -0.07962536594435504,
                    0.07653605315253799,
                    0.07894584158129836,
                    -0.07560098738084996
                ]
            }
        },
        {
            "number": 33,
            "state": {
                "two_finger_gripper": {
                    "pose": [
                        [
                            0.0,
                            0.0,
                            0.03
                        ],
                        [
                            0.0,
                            0.0,
                            0.0,
                            1.0
                        ]
                    ],
                    "joint_angles": {
                        "finger0_segment0_joint": -0.47730717149804053,
                        "finger0_segment1_joint": 0.9342248434724625,
                        "finger1_segment0_joint": 0.4770590738687763,
                        "finger1_segment1_joint": -0.9343787832579299
                    }
                },
                "obj_2": {
                    "pose": [
                        [
                            0.00012012827520164698,
                            0.1322841966286992,
                            0.04964387407151754
                        ],
                        [
                            -0.017471300206000167,
                            -5.7211656735995486e-05,
                            0.00022196853856289525,
                            0.9998473389102489
                        ]
                    ]
                }
            },
            "reward": {
                "distance_to_goal": 0.07345403600135231,
                "goal_position": [
                    0.0,
                    0.2067,
                    0
                ]
            },
            "action": {
                "target_joint_angles": [
                    -0.07962536594435504,
                    0.07653605315253799,
                    0.07894584158129836,
                    -0.07560098738084996
                ]
            }
        },
        {
            "number": 34,
            "state": {
                "two_finger_gripper": {
                    "pose": [
                        [
                            0.0,
                            0.0,
                            0.03
                        ],
                        [
                            0.0,
                            0.0,
                            0.0,
                            1.0
                        ]
                    ],
                    "joint_angles": {
                        "finger0_segment0_joint": -0.4654328514475928,
                        "finger0_segment1_joint": 0.9081699974917626,
                        "finger1_segment0_joint": 0.4651379064391271,
                        "finger1_segment1_joint": -0.9081990472639108
                    }
                },
                "obj_2": {
                    "pose": [
                        [
                            0.0001243994223203913,
                            0.13324606933817845,
                            0.04964422077091607
                        ],
                        [
                            -0.01747307757418716,
                            -6.565908898508471e-05,
                            0.00016394916268644237,
                            0.9998473185290055
                        ]
                    ]
                }
            },
            "reward": {
                "distance_to_goal": 0.07248659481491554,
                "goal_position": [
                    0.0,
                    0.2067,
                    0
                ]
            },
            "action": {
                "target_joint_angles": [
                    -0.07962536594435504,
                    0.07653605315253799,
                    0.07894584158129836,
                    -0.07560098738084996
                ]
            }
        },
        {
            "number": 35,
            "state": {
                "two_finger_gripper": {
                    "pose": [
                        [
                            0.0,
                            0.0,
                            0.03
                        ],
                        [
                            0.0,
                            0.0,
                            0.0,
                            1.0
                        ]
                    ],
                    "joint_angles": {
                        "finger0_segment0_joint": -0.45319896391554493,
                        "finger0_segment1_joint": 0.8813583694661725,
                        "finger1_segment0_joint": 0.4528685508275978,
                        "finger1_segment1_joint": -0.8813280632396919
                    }
                },
                "obj_2": {
                    "pose": [
                        [
                            0.00012988700323858892,
                            0.13421352155589203,
                            0.049644474117950144
                        ],
                        [
                            -0.017473430155809957,
                            -7.156204566750582e-05,
                            0.0001387849759304432,
                            0.9998473157718603
                        ]
                    ]
                }
            },
            "reward": {
                "distance_to_goal": 0.07151414745902633,
                "goal_position": [
                    0.0,
                    0.2067,
                    0
                ]
            },
            "action": {
                "target_joint_angles": [
                    -0.07962536594435504,
                    0.07653605315253799,
                    0.07894584158129836,
                    -0.07560098738084996
                ]
            }
        },
        {
            "number": 36,
            "state": {
                "two_finger_gripper": {
                    "pose": [
                        [
                            0.0,
                            0.0,
                            0.03
                        ],
                        [
                            0.0,
                            0.0,
                            0.0,
                            1.0
                        ]
                    ],
                    "joint_angles": {
                        "finger0_segment0_joint": -0.4405934280884012,
                        "finger0_segment1_joint": 0.8538053494546608,
                        "finger1_segment0_joint": 0.4401920742448925,
                        "finger1_segment1_joint": -0.8536698789158085
                    }
                },
                "obj_2": {
                    "pose": [
                        [
                            0.00013523204746964784,
                            0.13518598040184918,
                            0.04964464293326052
                        ],
                        [
                            -0.017473847635830216,
                            -7.517969674183031e-05,
                            9.689309014730121e-05,
                            0.9998473131476335
                        ]
                    ]
                }
            },
            "reward": {
                "distance_to_goal": 0.07053542618661826,
                "goal_position": [
                    0.0,
                    0.2067,
                    0
                ]
            },
            "action": {
                "target_joint_angles": [
                    -0.07962536594435504,
                    0.07653605315253799,
                    0.07894584158129836,
                    -0.07560098738084996
                ]
            }
        },
        {
            "number": 37,
            "state": {
                "two_finger_gripper": {
                    "pose": [
                        [
                            0.0,
                            0.0,
                            0.03
                        ],
                        [
                            0.0,
                            0.0,
                            0.0,
                            1.0
                        ]
                    ],
                    "joint_angles": {
                        "finger0_segment0_joint": -0.42754128945843256,
                        "finger0_segment1_joint": 0.8253699959421524,
                        "finger1_segment0_joint": 0.4270899126101951,
                        "finger1_segment1_joint": -0.8251698227503391
                    }
                },
                "obj_2": {
                    "pose": [
                        [
                            0.00013872650135649976,
                            0.136164710234623,
                            0.049644737402934624
                        ],
                        [
                            -0.017474136122699487,
                            -7.727972331758331e-05,
                            7.431735165546712e-05,
                            0.9998473098786339
                        ]
                    ]
                }
            },
            "reward": {
                "distance_to_goal": 0.06954915657178007,
                "goal_position": [
                    0.0,
                    0.2067,
                    0
                ]
            },
            "action": {
                "target_joint_angles": [
                    -0.07962536594435504,
                    0.07653605315253799,
                    0.07894584158129836,
                    -0.07560098738084996
                ]
            }
        },
        {
            "number": 38,
            "state": {
                "two_finger_gripper": {
                    "pose": [
                        [
                            0.0,
                            0.0,
                            0.03
                        ],
                        [
                            0.0,
                            0.0,
                            0.0,
                            1.0
                        ]
                    ],
                    "joint_angles": {
                        "finger0_segment0_joint": -0.4140182576877181,
                        "finger0_segment1_joint": 0.7959940868246355,
                        "finger1_segment0_joint": 0.4134829913790693,
                        "finger1_segment1_joint": -0.7956644744356235
                    }
                },
                "obj_2": {
                    "pose": [
                        [
                            0.00014196145640194596,
                            0.13715098831190428,
                            0.049644776978943234
                        ],
                        [
                            -0.017474065620912405,
                            -7.742839402789201e-05,
                            2.6907872280718808e-05,
                            0.9998473134991593
                        ]
                    ]
                }
            },
            "reward": {
                "distance_to_goal": 0.0685530659639427,
                "goal_position": [
                    0.0,
                    0.2067,
                    0
                ]
            },
            "action": {
                "target_joint_angles": [
                    -0.07962536594435504,
                    0.07653605315253799,
                    0.07894584158129836,
                    -0.07560098738084996
                ]
            }
        },
        {
            "number": 39,
            "state": {
                "two_finger_gripper": {
                    "pose": [
                        [
                            0.0,
                            0.0,
                            0.03
                        ],
                        [
                            0.0,
                            0.0,
                            0.0,
                            1.0
                        ]
                    ],
                    "joint_angles": {
                        "finger0_segment0_joint": -0.39996424824606464,
                        "finger0_segment1_joint": 0.7655155091381577,
                        "finger1_segment0_joint": 0.39935096336942244,
                        "finger1_segment1_joint": -0.7650138200822129
                    }
                },
                "obj_2": {
                    "pose": [
                        [
                            0.00014354142050296338,
                            0.13814708431498132,
                            0.049644759638510505
                        ],
                        [
                            -0.017471629203826302,
                            -7.442906105945693e-05,
                            -3.761021216716582e-05,
                            0.9998473559592739
                        ]
                    ]
                }
            },
            "reward": {
                "distance_to_goal": 0.06754827460578558,
                "goal_position": [
                    0.0,
                    0.2067,
                    0
                ]
            },
            "action": {
                "target_joint_angles": [
                    -0.07962536594435504,
                    0.07653605315253799,
                    0.07894584158129836,
                    -0.07560098738084996
                ]
            }
        },
        {
            "number": 40,
            "state": {
                "two_finger_gripper": {
                    "pose": [
                        [
                            0.0,
                            0.0,
                            0.03
                        ],
                        [
                            0.0,
                            0.0,
                            0.0,
                            1.0
                        ]
                    ],
                    "joint_angles": {
                        "finger0_segment0_joint": -0.38531348758402856,
                        "finger0_segment1_joint": 0.733851787296761,
                        "finger1_segment0_joint": 0.3846168144957155,
                        "finger1_segment1_joint": -0.7331197928946838
                    }
                },
                "obj_2": {
                    "pose": [
                        [
                            0.0001407986403110024,
                            0.13915187213577637,
                            0.049645222502557276
                        ],
                        [
                            -0.017457108524869713,
                            -7.491425729715626e-05,
                            -0.00013296041022173375,
                            0.999847601423004
                        ]
                    ]
                }
            },
            "reward": {
                "distance_to_goal": 0.06654650251443865,
                "goal_position": [
                    0.0,
                    0.2067,
                    0
                ]
            },
            "action": {
                "target_joint_angles": [
                    -0.07962536594435504,
                    0.07653605315253799,
                    0.07894584158129836,
                    -0.07560098738084996
                ]
            }
        },
        {
            "number": 41,
            "state": {
                "two_finger_gripper": {
                    "pose": [
                        [
                            0.0,
                            0.0,
                            0.03
                        ],
                        [
                            0.0,
                            0.0,
                            0.0,
                            1.0
                        ]
                    ],
                    "joint_angles": {
                        "finger0_segment0_joint": -0.36996614073598194,
                        "finger0_segment1_joint": 0.7007918452731179,
                        "finger1_segment0_joint": 0.36918596059055747,
                        "finger1_segment1_joint": -0.7000070958257325
                    }
                },
                "obj_2": {
                    "pose": [
                        [
                            0.0001349311403897552,
                            0.140153634280364,
                            0.049643677684202206
                        ],
                        [
                            -0.01753377529093506,
                            1.997570696035816e-05,
                            0.0001467032858697997,
                            0.999846260583678
                        ]
                    ]
                }
            },
            "reward": {
                "distance_to_goal": 0.06551457630601493,
                "goal_position": [
                    0.0,
                    0.2067,
                    0
                ]
            },
            "action": {
                "target_joint_angles": [
                    -0.07962536594435504,
                    0.07653605315253799,
                    0.07894584158129836,
                    -0.07560098738084996
                ]
            }
        },
        {
            "number": 42,
            "state": {
                "two_finger_gripper": {
                    "pose": [
                        [
                            0.0,
                            0.0,
                            0.03
                        ],
                        [
                            0.0,
                            0.0,
                            0.0,
                            1.0
                        ]
                    ],
                    "joint_angles": {
                        "finger0_segment0_joint": -0.35384544033313475,
                        "finger0_segment1_joint": 0.6659815627431204,
                        "finger1_segment0_joint": 0.35297156875120633,
                        "finger1_segment1_joint": -0.6650681024069917
                    }
                },
                "obj_2": {
                    "pose": [
                        [
                            0.00013422023124563053,
                            0.14118556118315462,
                            0.049643783363498506
                        ],
                        [
                            -0.01753026882321562,
                            1.809820544055826e-05,
                            0.00011402867557154819,
                            0.9998463263646579
                        ]
                    ]
                }
            },
            "reward": {
                "distance_to_goal": 0.06448300676459387,
                "goal_position": [
                    0.0,
                    0.2067,
                    0
                ]
            },
            "action": {
                "target_joint_angles": [
                    -0.07962536594435504,
                    0.07653605315253799,
                    0.07894584158129836,
                    -0.07560098738084996
                ]
            }
        },
        {
            "number": 43,
            "state": {
                "two_finger_gripper": {
                    "pose": [
                        [
                            0.0,
                            0.0,
                            0.03
                        ],
                        [
                            0.0,
                            0.0,
                            0.0,
                            1.0
                        ]
                    ],
                    "joint_angles": {
                        "finger0_segment0_joint": -0.33677379329411333,
                        "finger0_segment1_joint": 0.629191708049694,
                        "finger1_segment0_joint": 0.33586398164021536,
                        "finger1_segment1_joint": -0.6283261110387895
                    }
                },
                "obj_2": {
                    "pose": [
                        [
                            0.00014441470579215396,
                            0.14221715494958825,
                            0.049643847482978606
                        ],
                        [
                            -0.017450027934504633,
                            7.114829771697774e-05,
                            -0.00017948002981928147,
                            0.9998477180300627
                        ]
                    ]
                }
            },
            "reward": {
                "distance_to_goal": 0.06346581834127499,
                "goal_position": [
                    0.0,
                    0.2067,
                    0
                ]
            },
            "action": {
                "target_joint_angles": [
                    -0.07962536594435504,
                    0.07653605315253799,
                    0.07894584158129836,
                    -0.07560098738084996
                ]
            }
        },
        {
            "number": 44,
            "state": {
                "two_finger_gripper": {
                    "pose": [
                        [
                            0.0,
                            0.0,
                            0.03
                        ],
                        [
                            0.0,
                            0.0,
                            0.0,
                            1.0
                        ]
                    ],
                    "joint_angles": {
                        "finger0_segment0_joint": -0.31856304364024673,
                        "finger0_segment1_joint": 0.5900710083770194,
                        "finger1_segment0_joint": 0.3176001004000034,
                        "finger1_segment1_joint": -0.5891295513339095
                    }
                },
                "obj_2": {
                    "pose": [
                        [
                            0.00015553797095081763,
                            0.14323437225026991,
                            0.04963369107696586
                        ],
                        [
                            -0.017408289368933596,
                            -0.00016321107430214096,
                            -0.0010323995740480806,
                            0.9998479179227769
                        ]
                    ]
                }
            },
            "reward": {
                "distance_to_goal": 0.06252231690605162,
                "goal_position": [
                    0.0,
                    0.2067,
                    0
                ]
            },
            "action": {
                "target_joint_angles": [
                    -0.07962536594435504,
                    0.07653605315253799,
                    0.07894584158129836,
                    -0.07560098738084996
                ]
            }
        },
        {
            "number": 45,
            "state": {
                "two_finger_gripper": {
                    "pose": [
                        [
                            0.0,
                            0.0,
                            0.03
                        ],
                        [
                            0.0,
                            0.0,
                            0.0,
                            1.0
                        ]
                    ],
                    "joint_angles": {
                        "finger0_segment0_joint": -0.2988518872723528,
                        "finger0_segment1_joint": 0.547835341124882,
                        "finger1_segment0_joint": 0.2978730789001056,
                        "finger1_segment1_joint": -0.5468329478054217
                    }
                },
                "obj_2": {
                    "pose": [
                        [
                            0.00016167269967152037,
                            0.14417789212415397,
                            0.04963999297932546
                        ],
                        [
                            -0.017581157870724475,
                            -0.00012119615742751931,
                            -0.001500255987834359,
                            0.9998443065954755
                        ]
                    ]
                }
            },
            "reward": {
                "distance_to_goal": 0.06163870302284479,
                "goal_position": [
                    0.0,
                    0.2067,
                    0
                ]
            },
            "action": {
                "target_joint_angles": [
                    -0.07962536594435504,
                    0.07653605315253799,
                    0.07894584158129836,
                    -0.07560098738084996
                ]
            }
        },
        {
            "number": 46,
            "state": {
                "two_finger_gripper": {
                    "pose": [
                        [
                            0.0,
                            0.0,
                            0.03
                        ],
                        [
                            0.0,
                            0.0,
                            0.0,
                            1.0
                        ]
                    ],
                    "joint_angles": {
                        "finger0_segment0_joint": -0.2769352708361684,
                        "finger0_segment1_joint": 0.5006247753930881,
                        "finger1_segment0_joint": 0.2759844209510589,
                        "finger1_segment1_joint": -0.4996546265294749
                    }
                },
                "obj_2": {
                    "pose": [
                        [
                            0.00015711511557278449,
                            0.14506149721822476,
                            0.049628855936229545
                        ],
                        [
                            -0.018132117329139875,
                            0.0006700867610373221,
                            -0.00046077049370436205,
                            0.9998352689295608
                        ]
                    ]
                }
            },
            "reward": {
                "distance_to_goal": 0.060872553139949236,
                "goal_position": [
                    0.0,
                    0.2067,
                    0
                ]
            },
            "action": {
                "target_joint_angles": [
                    -0.07962536594435504,
                    0.07653605315253799,
                    0.07894584158129836,
                    -0.07560098738084996
                ]
            }
        }
    ]
}